torchlight/__init__.py
torchlight/version.py
torchlight/contrib/__init__.py
torchlight/contrib/basicsr_data/__init__.py
torchlight/contrib/basicsr_data/data_sampler.py
torchlight/contrib/basicsr_data/data_util.py
torchlight/contrib/basicsr_data/ffhq_dataset.py
torchlight/contrib/basicsr_data/paired_image_SR_LR_FullImage_Memory_dataset.py
torchlight/contrib/basicsr_data/paired_image_SR_LR_dataset.py
torchlight/contrib/basicsr_data/paired_image_dataset.py
torchlight/contrib/basicsr_data/prefetch_dataloader.py
torchlight/contrib/basicsr_data/reds_dataset.py
torchlight/contrib/basicsr_data/single_image_dataset.py
torchlight/contrib/basicsr_data/transforms.py
torchlight/contrib/basicsr_data/video_test_dataset.py
torchlight/contrib/basicsr_data/vimeo90k_dataset.py
torchlight/contrib/datasets/ICVL.py
torchlight/contrib/datasets/SIDD.py
torchlight/contrib/datasets/__init__.py
torchlight/contrib/scripts/SIDD_test.py
torchlight/contrib/scripts/__init__.py
torchlight/contrib/scripts/mnist.py
torchlight/contrib/utils/__init__.py
torchlight/contrib/utils/hsi.py
torchlight/data/__init__.py
torchlight/data/dataloader.py
torchlight/data/dataset.py
torchlight/data/image_folder.py
torchlight/data/datasets/__init__.py
torchlight/data/datasets/pair.py
torchlight/data/datasets/wrapper.py
torchlight/logging/__init__.py
torchlight/logging/logger.py
torchlight/logging/visualization.py
torchlight/metrics/__init__.py
torchlight/metrics/_util.py
torchlight/metrics/simple.py
torchlight/metrics/torch.py
torchlight/nn/__init__.py
torchlight/nn/benchmark.py
torchlight/nn/conversion.py
torchlight/nn/init.py
torchlight/nn/lr_scheduler.py
torchlight/nn/reproducibility.py
torchlight/nn/utils.py
torchlight/nn/blocks/__init__.py
torchlight/nn/blocks/residual.py
torchlight/nn/blocks/upsample.py
torchlight/nn/loss/__init__.py
torchlight/nn/loss/landmark.py
torchlight/nn/loss/misc.py
torchlight/nn/loss/vggloss.py
torchlight/nn/loss/functional/__init__.py
torchlight/nn/loss/functional/misc.py
torchlights-0.4.0.dist-info/METADATA
torchlights-0.4.0.dist-info/WHEEL
torchlights-0.4.0.dist-info/top_level.txt
torchlights-0.4.0.dist-info/RECORD
