Metadata-Version: 2.1
Name: torchlights
Version: 0.4.0
Summary: Torchlights - an light-weight PyTorch trainer, as well as many useful utils
Home-page: https://github.com/Zeqiang-Lai/torchlight
Author: Zeqiang Lai
Author-email: laizeqiang@outlook.com
Requires-Dist: munch
Requires-Dist: colorama
Requires-Dist: readchar
Requires-Dist: tqdm
Requires-Dist: qqdm
Requires-Dist: pyyaml
Requires-Dist: colorlog
